ears/__init__.py
ears/events.py
ears/handlers.py
ears/messaging.py
ears/models.py
ears/providers/__init__.py
ears/providers/beatport.py
ears/providers/deezer.py
ears/types.py
ears-0.2.10.dist-info/WHEEL
ears-0.2.10.dist-info/METADATA
ears-0.2.10.dist-info/RECORD
