Metadata-Version: 2.1
Name: ears
Version: 0.2.10
Summary: 
Author: Félix Voituret
Author-email: fvoituret@deezer.com
Requires-Python: >=3.9,<4.0
Classifier: Programming Language :: Python :: 3
Classifier: Programming Language :: Python :: 3.9
Classifier: Programming Language :: Python :: 3.10
Requires-Dist: Flask (>=2.2.2,<3.0.0)
Requires-Dist: google-cloud-pubsub (>=2.13.7,<3.0.0)
Requires-Dist: httpx (>=0.23.0,<0.24.0)
Requires-Dist: pydantic (>=1.10.2,<2.0.0)
